locales/de.po
locales/en.po
locales/es.po
locales/fr.po
locales/nb_NO.po
locales/strings.pot
locales/zh_Hans.po
nextcloud_talk_bot/Nextcloudtalkbot.py
nextcloud_talk_bot/__init__.py
nextcloud_talk_bot/check_local_user_enviroment.py
nextcloud_talk_bot/confirmation.py
nextcloud_talk_bot/conversations_map.py
nextcloud_talk_bot/first_run_setup.py
nextcloud_talk_bot/headers.py
nextcloud_talk_bot/i18n.py
nextcloud_talk_bot/ncbot.py
nextcloud_talk_bot/nextcloud_activities.py
nextcloud_talk_bot/nextcloud_calendar.py
nextcloud_talk_bot/nextcloud_data.py
nextcloud_talk_bot/nextcloud_file_operations.py
nextcloud_talk_bot/nextcloud_meeting.py
nextcloud_talk_bot/nextcloud_messages.py
nextcloud_talk_bot/nextcloud_monitoring.py
nextcloud_talk_bot/nextcloud_poll.py
nextcloud_talk_bot/nextcloud_requests.py
nextcloud_talk_bot/nextcloud_search.py
nextcloud_talk_bot/nextcloud_talk_extractor.py
nextcloud_talk_bot/nextcloud_user.py
nextcloud_talk_bot/permissions_map.py
nextcloud_talk_bot/translations.py
tests/__init__.py
tests/integration_test.py
tests/test_confirmation.py
tests/test_first_run_setup.py
tests/test_nextcloud_activities.py
tests/test_nextcloud_meeting.py
tests/test_nextcloud_monitoring.py
tests/test_nextcloud_poll.py
tests/test_nextcloud_requests.py
tests/test_nextcloud_talk_extractor.py
tests/test_nextcloud_user.py
nextcloudtalkbot-0.0.46.dist-info/METADATA
nextcloudtalkbot-0.0.46.dist-info/WHEEL
nextcloudtalkbot-0.0.46.dist-info/licenses/LICENSE
nextcloudtalkbot-0.0.46.dist-info/RECORD
