Metadata-Version: 2.1
Name: nextcloudtalkbot
Version: 0.0.46
Summary: Python3 library for creating a Nextcloud Talk bot.
Project-URL: Homepage, https://github.com/sowoi/nextcloud-talk-bot
Project-URL: Bug Tracker, https://github.com/sowoi/nextcloud-talk-bot/issues
Project-URL: Documentation, https://nextcloud-talk-bot.readthedocs.io
Author-email: Massoud Ahmed <okko@okxo.de>
License-File: LICENSE
Keywords: bot,nextcloud,nextcloud talk
Classifier: Development Status :: 3 - Alpha
Classifier: Intended Audience :: Developers
Classifier: License :: OSI Approved :: GNU General Public License v3 (GPLv3)
Classifier: Operating System :: OS Independent
Classifier: Programming Language :: Python :: 3.8
Classifier: Programming Language :: Python :: 3.9
Classifier: Programming Language :: Python :: 3.10
Requires-Python: >=3.7
Requires-Dist: caldav
Requires-Dist: cryptography
Requires-Dist: icalendar
Requires-Dist: python-dateutil
Requires-Dist: requests
Requires-Dist: requests-cache
Requires-Dist: spacy
Requires-Dist: vobject
